oneNeuron/Perceptron.py
oneNeuron/__init__.py
oneNeuron_umangtank-0.0.2.dist-info/LICENSE
oneNeuron_umangtank-0.0.2.dist-info/METADATA
oneNeuron_umangtank-0.0.2.dist-info/WHEEL
oneNeuron_umangtank-0.0.2.dist-info/top_level.txt
oneNeuron_umangtank-0.0.2.dist-info/RECORD
