Metadata-Version: 2.1
Name: oneNeuron-umangtank
Version: 0.0.2
Summary: It's an Implimentation of Perceptron
Home-page: https://github.com/umangtank/oneNeuron
Author: umangtank
Author-email: umangtank08@gmail.com
License: UNKNOWN
Project-URL: Bug Tracker, https://github.com/umangtank/oneNeuron
Platform: UNKNOWN
Classifier: Programming Language :: Python :: 3
Classifier: License :: OSI Approved :: MIT License
Classifier: Operating System :: OS Independent
Requires-Python: >=3.7
License-File: LICENSE
Requires-Dist: numpy
Requires-Dist: tqdm
